LICENSE
README.md
pyproject.toml
setup.py
src/pywebsoc.egg-info/PKG-INFO
src/pywebsoc.egg-info/SOURCES.txt
src/pywebsoc.egg-info/dependency_links.txt
src/pywebsoc.egg-info/requires.txt
src/pywebsoc.egg-info/top_level.txt
src/websocAPI/__init__.py
src/websocAPI/utils.py
src/websocAPI/webscrape.py