Metadata-Version: 2.1
Name: pywebsoc
Version: 0.0.12
Summary: UCI WebSoc API and Other Packages
Home-page: https://github.com/printSANO/pywebsoc
Author: Ryan Lee, Anastacio Ruiz, Ernest Yao
Author-email: rhahnwoonglee@gmail.com
Project-URL: Bug Tracker, https://github.com/printSANO/pywebsoc/issues
Project-URL: repository, https://github.com/printSANO/pywebsoc
Classifier: Programming Language :: Python :: 3
Classifier: License :: OSI Approved :: Apache Software License
Classifier: Operating System :: OS Independent
Requires-Python: >=3.6
License-File: LICENSE
